Final Project/hardware/MAC.sv
module mac_16 #(parameter OUT_BIT = 32, parameter LOW_PRE = 0, parameter INWID = 4)(
    input logic clk, reset,
    input logic [1:0] ctrl,
    input wire [INWID*4-1:0] a,
    input wire [INWID*4-1:0] b,
    output reg [OUT_BIT-1:0] out
);
    // out regs
    reg [OUT_BIT-1:0] c[15:0];
    reg [OUT_BIT-1:0] out_c;

    genvar i,j;
    integer k;

    // map a b bits to 4-bit multipliers, accum 16 mul and mul16 are differnet
    generate
    if(!LOW_PRE)
        for(i=0; i<4; i=i+1) 
            for(j=0; j<4; j=j+1) 
            begin: mac_gen
                mul_4 mul_4bit(
                    .clk(clk), 
                    .reset(reset), 
                    .a   (a[i*4+3:i*4]),
                    .b   (b[j*4+3:j*4]),
                    .c   (c[j+i*4][7:0]));
            end
    else
        for(i=0; i<16; i=i+1) 
        begin: mac_gen_low
            mul_4 mul_4bit(
                .clk(clk), 
                .reset(reset), 
                .a   (a[i*4+3:i*4]),
                .b   (b[i*4+3:i*4]),
                .c   (c[i][7:0]));
        end
    endgenerate

    // initialize intermidiate out
    initial begin
        if(!LOW_PRE) begin 
            for (k=0;k<16;k=k+1) c[k][OUT_BIT-1:8] = 0;
        end
    end
    // output selection
    always_comb begin
        if (~reset) begin
            out_c = 0;
        end
        else begin
            case(ctrl) 
                2'b00: if(!LOW_PRE) out_c = 0;  // projection input is 0, out is 0
                2'b01: if(!LOW_PRE) out_c = {16'b0,a}; // projection input is 1, out is in
                2'b10: if(!LOW_PRE) out_c = -{16'b0,a}; // projection input is -1, out is -in
                2'b11: begin 
                    if(!LOW_PRE) begin
                        out_c =  c[0]        + (c[1]<<4)   + (c[4]<<4) 
                                + (c[2]<<8)   + (c[5]<<8)   + (c[8]<<8)
                                + (c[3]<<12)  + (c[6]<<12)  + (c[9]<<12) + (c[12]<<12) 
                                + (c[7]<<16)  + (c[10]<<16) + (c[13]<<16) 
                                + (c[11]<<20) + (c[14]<<20) + (c[15]<<24) ;
                        //out_c <= out_c + acc;
                    end
                    else out_c = c[0] + c[1] + c[2] + c[3]
                                + c[4] + c[5] + c[6] + c[7]
                                + c[8] + c[9] + c[10] + c[11]
                                + c[12] + c[13] + c[14] + c[15];
                    end
                default: out_c = 0;
            endcase

        end 
    end

    assign out = out_c;
endmodule

module mul_4(
    input  logic clk, reset,
    input  wire [3:0] a,b, 
    output reg [7:0] c
);
  always_comb
    if (~reset) begin
        c = 0;
    end
    else begin
        c = (a * b);
    end
endmodule

Final Project/hardware/mul_tb.sv

module test_mul_4;

    // Signals
    logic clk;
    logic reset;
    reg [3:0] a, b;
    wire [7:0] c;


    // Instantiate the DUT
    mul_4 dut (
        .clk(clk),
        .reset(reset),
        .a(a),
        .b(b),
        .c(c)
    );

    // Clock generation
    always #5 clk = ~clk;

    // Reset generation
    initial begin
        clk = 0;
        reset = 1;
        #20
        reset = 0;
        #20;
        reset = 1;
    end

    // VCD file generation
    initial begin
        $dumpfile("mul_4_simulation.vcd");
        $dumpvars(0, test_mul_4);
    end

    // Test stimulus
    initial begin
        // Wait for initial reset to complete
        #100;

        // Main test loop
        repeat (10) begin
            // Generate random inputs
            a = $urandom_range(0, 7);
            b = $urandom_range(0, 7);
           

            // Wait a few clock cycles
            #5;

            // Print inputs
            $display("Input: a=%h, b=%h", a, b);

            // Print output
            $display("Output: out=%h", c);
        end

        // End simulation
        $finish;
    end

endmodule

Final Project/hardware/mul_4_simulation.vcd
$date
	Tue Apr 02 11:03:25 2024
$end
$version
	ModelSim Version 2020.1
$end
$timescale
	1ps
$end

$scope module test_mul_4 $end
$var reg 1 ! clk $end
$var reg 1 " reset $end
$var reg 4 # a [3:0] $end
$var reg 4 $ b [3:0] $end
$var wire 1 % c [7] $end
$var wire 1 & c [6] $end
$var wire 1 ' c [5] $end
$var wire 1 ( c [4] $end
$var wire 1 ) c [3] $end
$var wire 1 * c [2] $end
$var wire 1 + c [1] $end
$var wire 1 , c [0] $end

$scope module dut $end
$var wire 1 - clk $end
$var wire 1 . reset $end
$var wire 1 / a [3] $end
$var wire 1 0 a [2] $end
$var wire 1 1 a [1] $end
$var wire 1 2 a [0] $end
$var wire 1 3 b [3] $end
$var wire 1 4 b [2] $end
$var wire 1 5 b [1] $end
$var wire 1 6 b [0] $end
$var reg 8 7 c [7:0] $end
$upscope $end
$upscope $end
$enddefinitions $end
#0
$dumpvars
0!
1"
bx #
bx $
bx 7
x,
x+
x*
x)
x(
x'
x&
x%
0-
1.
x2
x1
x0
x/
x6
x5
x4
x3
$end
#5
1!
1-
#10
0!
0-
#15
1!
1-
#20
0"
0!
0-
0.
b0 7
0,
0+
0*
0)
0(
0'
0&
0%
#25
1!
1-
#30
0!
0-
#35
1!
1-
#40
1"
0!
0-
1.
bx 7
x,
x+
x*
x)
x(
x'
x&
x%
#45
1!
1-
#50
0!
0-
#55
1!
1-
#60
0!
0-
#65
1!
1-
#70
0!
0-
#75
1!
1-
#80
0!
0-
#85
1!
1-
#90
0!
0-
#95
1!
1-
#100
b110 #
b0 $
0!
0-
06
05
04
03
02
11
10
0/
b0 7
0,
0+
0*
0)
0(
0'
0&
0%
#105
b10 #
b100 $
1!
1-
14
00
b1000 7
1)
#110
b100 #
b111 $
0!
0-
16
15
01
10
b11100 7
1*
1(
#115
b11 #
b101 $
1!
1-
05
12
11
00
b1111 7
1,
1+
0(
#120
b100 $
0!
0-
06
b1100 7
0,
0+
#125
b111 #
b11 $
1!
1-
16
15
04
10
b10101 7
1,
0)
1(
#130
b0 #
b0 $
0!
0-
06
05
02
01
00
b0 7
0,
0*
0(
#135
b10 #
b10 $
1!
1-
15
11
b100 7
1*
#140
b1 #
b1 $
0!
0-
16
05
12
01
b1 7
1,
0*
#145
b111 #
b100 $
1!
1-
06
14
11
10
b11100 7
0,
1*
1)
1(
